{"name":"worldbank_gender-statistics","title":"Gender Statistics","description":"The Gender Statistics database is a comprehensive source for the latest sex-disaggregated data and gender statistics covering demography, education, health, access to economic opportunities, public life and decision-making, and agency.\n\n__*Source:*__ http://data.worldbank.org/data-catalog/gender-statistics\n\n[World Bank Data Catalog Terms of Use](http://web.worldbank.org/WBSITE/EXTERNAL/0,,contentMDK:22547097~pagePK:50016803~piPK:50016805~theSitePK:13,00.html)","homepage":"https://data.world/worldbank/gender-statistics","license":"CCBy","resources":[{"name":"gender_stat_country","schema":{"fields":[{"name":"country_code","title":"Country Code","type":"string","rdfType":"http://www.w3.org/2001/XMLSchema#string","dwSourceId":"country_code"},{"name":"short_name","title":"Short Name","type":"string","rdfType":"http://www.w3.org/2001/XMLSchema#string","dwSourceId":"short_name"},{"name":"table_name","title":"Table Name","type":"string","rdfType":"http://www.w3.org/2001/XMLSchema#string","dwSourceId":"table_name"},{"name":"long_name","title":"Long Name","type":"string","rdfType":"http://www.w3.org/2001/XMLSchema#string","dwSourceId":"long_name"},{"name":"2_alpha_code","title":"2-alpha code","type":"string","rdfType":"http://www.w3.org/2001/XMLSchema#string","dwSourceId":"2_alpha_code"},{"name":"currency_unit","title":"Currency Unit","type":"string","rdfType":"http://www.w3.org/2001/XMLSchema#string","dwSourceId":"currency_unit"},{"name":"special_notes","title":"Special Notes","type":"string","rdfType":"http://www.w3.org/2001/XMLSchema#string","dwSourceId":"special_notes"},{"name":"region","title":"Region","type":"string","rdfType":"http://www.w3.org/2001/XMLSchema#string","dwSourceId":"region"},{"name":"income_group","title":"Income Group","type":"string","rdfType":"http://www.w3.org/2001/XMLSchema#string","dwSourceId":"income_group"},{"name":"wb_2_code","title":"WB-2 code","type":"string","rdfType":"http://www.w3.org/2001/XMLSchema#string","dwSourceId":"wb_2_code"},{"name":"national_accounts_base_year","title":"National accounts base year","type":"string","rdfType":"http://www.w3.org/2001/XMLSchema#string","dwSourceId":"national_accounts_base_year"},{"name":"national_accounts_reference_year","title":"National accounts reference year","type":"string","rdfType":"http://www.w3.org/2001/XMLSchema#string","dwSourceId":"national_accounts_reference_year"},{"name":"sna_price_valuation","title":"SNA price valuation","type":"string","rdfType":"http://www.w3.org/2001/XMLSchema#string","dwSourceId":"sna_price_valuation"},{"name":"lending_category","title":"Lending category","type":"string","rdfType":"http://www.w3.org/2001/XMLSchema#string","dwSourceId":"lending_category"},{"name":"other_groups","title":"Other groups","type":"string","rdfType":"http://www.w3.org/2001/XMLSchema#string","dwSourceId":"other_groups"},{"name":"system_of_national_accounts","title":"System of National Accounts","type":"string","rdfType":"http://www.w3.org/2001/XMLSchema#string","dwSourceId":"system_of_national_accounts"},{"name":"alternative_conversion_factor","title":"Alternative conversion factor","type":"string","rdfType":"http://www.w3.org/2001/XMLSchema#string","dwSourceId":"alternative_conversion_factor"},{"name":"ppp_survey_year","title":"PPP survey year","type":"string","rdfType":"http://www.w3.org/2001/XMLSchema#string","dwSourceId":"ppp_survey_year"},{"name":"balance_of_payments_manual_in_use","title":"Balance of Payments Manual in use","type":"string","rdfType":"http://www.w3.org/2001/XMLSchema#string","dwSourceId":"balance_of_payments_manual_in_use"},{"name":"external_debt_reporting_status","title":"External debt Reporting status","type":"string","rdfType":"http://www.w3.org/2001/XMLSchema#string","dwSourceId":"external_debt_reporting_status"},{"name":"system_of_trade","title":"System of trade","type":"string","rdfType":"http://www.w3.org/2001/XMLSchema#string","dwSourceId":"system_of_trade"},{"name":"government_accounting_concept","title":"Government Accounting concept","type":"string","rdfType":"http://www.w3.org/2001/XMLSchema#string","dwSourceId":"government_accounting_concept"},{"name":"imf_data_dissemination_standard","title":"IMF data dissemination standard","type":"string","rdfType":"http://www.w3.org/2001/XMLSchema#string","dwSourceId":"imf_data_dissemination_standard"},{"name":"latest_population_census","title":"Latest population census","type":"string","rdfType":"http://www.w3.org/2001/XMLSchema#string","dwSourceId":"latest_population_census"},{"name":"latest_household_survey","title":"Latest household survey","type":"string","rdfType":"http://www.w3.org/2001/XMLSchema#string","dwSourceId":"latest_household_survey"},{"name":"source_of_most_recent_income_and_expenditure_data","title":"Source of most recent Income and expenditure data","type":"string","rdfType":"http://www.w3.org/2001/XMLSchema#string","dwSourceId":"source_of_most_recent_income_and_expenditure_data"},{"name":"vital_registration_complete","title":"Vital registration complete","type":"string","rdfType":"http://www.w3.org/2001/XMLSchema#string","dwSourceId":"vital_registration_complete"},{"name":"latest_agricultural_census","title":"Latest agricultural census","type":"string","rdfType":"http://www.w3.org/2001/XMLSchema#string","dwSourceId":"latest_agricultural_census"},{"name":"latest_industrial_data","title":"Latest industrial data","type":"integer","rdfType":"http://www.w3.org/2001/XMLSchema#integer","dwSourceId":"latest_industrial_data"},{"name":"latest_trade_data","title":"Latest trade data","type":"integer","rdfType":"http://www.w3.org/2001/XMLSchema#integer","dwSourceId":"latest_trade_data"},{"name":"latest_water_withdrawal_data","title":"Latest water withdrawal data","type":"integer","rdfType":"http://www.w3.org/2001/XMLSchema#integer","dwSourceId":"latest_water_withdrawal_data"}]},"path":"data/gender_stat_country.csv","format":"csv"},{"name":"gender_stat_country_series","schema":{"fields":[{"name":"countrycode","title":"CountryCode","type":"string","rdfType":"http://www.w3.org/2001/XMLSchema#string","dwSourceId":"countrycode"},{"name":"seriescode","title":"SeriesCode","type":"string","rdfType":"http://www.w3.org/2001/XMLSchema#string","dwSourceId":"seriescode"},{"name":"description","title":"DESCRIPTION","type":"string","rdfType":"http://www.w3.org/2001/XMLSchema#string","dwSourceId":"description"}]},"path":"data/gender_stat_country_series.csv","format":"csv"},{"name":"gender_stat_data","schema":{"fields":[{"name":"country_name","title":"Country Name","type":"string","rdfType":"http://www.w3.org/2001/XMLSchema#string","dwSourceId":"country_name"},{"name":"country_code","title":"Country Code","type":"string","rdfType":"http://www.w3.org/2001/XMLSchema#string","dwSourceId":"country_code"},{"name":"indicator_name","title":"Indicator Name","type":"string","rdfType":"http://www.w3.org/2001/XMLSchema#string","dwSourceId":"indicator_name"},{"name":"indicator_code","title":"Indicator Code","type":"string","rdfType":"http://www.w3.org/2001/XMLSchema#string","dwSourceId":"indicator_code"},{"name":"1960","title":"1960","type":"number","rdfType":"http://www.w3.org/2001/XMLSchema#decimal","dwSourceId":"1960"},{"name":"1961","title":"1961","type":"number","rdfType":"http://www.w3.org/2001/XMLSchema#decimal","dwSourceId":"1961"},{"name":"1962","title":"1962","type":"number","rdfType":"http://www.w3.org/2001/XMLSchema#decimal","dwSourceId":"1962"},{"name":"1963","title":"1963","type":"number","rdfType":"http://www.w3.org/2001/XMLSchema#decimal","dwSourceId":"1963"},{"name":"1964","title":"1964","type":"number","rdfType":"http://www.w3.org/2001/XMLSchema#decimal","dwSourceId":"1964"},{"name":"1965","title":"1965","type":"number","rdfType":"http://www.w3.org/2001/XMLSchema#decimal","dwSourceId":"1965"},{"name":"1966","title":"1966","type":"number","rdfType":"http://www.w3.org/2001/XMLSchema#decimal","dwSourceId":"1966"},{"name":"1967","title":"1967","type":"number","rdfType":"http://www.w3.org/2001/XMLSchema#decimal","dwSourceId":"1967"},{"name":"1968","title":"1968","type":"number","rdfType":"http://www.w3.org/2001/XMLSchema#decimal","dwSourceId":"1968"},{"name":"1969","title":"1969","type":"number","rdfType":"http://www.w3.org/2001/XMLSchema#decimal","dwSourceId":"1969"},{"name":"1970","title":"1970","type":"number","rdfType":"http://www.w3.org/2001/XMLSchema#decimal","dwSourceId":"1970"},{"name":"1971","title":"1971","type":"number","rdfType":"http://www.w3.org/2001/XMLSchema#decimal","dwSourceId":"1971"},{"name":"1972","title":"1972","type":"number","rdfType":"http://www.w3.org/2001/XMLSchema#decimal","dwSourceId":"1972"},{"name":"1973","title":"1973","type":"number","rdfType":"http://www.w3.org/2001/XMLSchema#decimal","dwSourceId":"1973"},{"name":"1974","title":"1974","type":"number","rdfType":"http://www.w3.org/2001/XMLSchema#decimal","dwSourceId":"1974"},{"name":"1975","title":"1975","type":"number","rdfType":"http://www.w3.org/2001/XMLSchema#decimal","dwSourceId":"1975"},{"name":"1976","title":"1976","type":"number","rdfType":"http://www.w3.org/2001/XMLSchema#decimal","dwSourceId":"1976"},{"name":"1977","title":"1977","type":"number","rdfType":"http://www.w3.org/2001/XMLSchema#decimal","dwSourceId":"1977"},{"name":"1978","title":"1978","type":"number","rdfType":"http://www.w3.org/2001/XMLSchema#decimal","dwSourceId":"1978"},{"name":"1979","title":"1979","type":"number","rdfType":"http://www.w3.org/2001/XMLSchema#decimal","dwSourceId":"1979"},{"name":"1980","title":"1980","type":"number","rdfType":"http://www.w3.org/2001/XMLSchema#decimal","dwSourceId":"1980"},{"name":"1981","title":"1981","type":"number","rdfType":"http://www.w3.org/2001/XMLSchema#decimal","dwSourceId":"1981"},{"name":"1982","title":"1982","type":"number","rdfType":"http://www.w3.org/2001/XMLSchema#decimal","dwSourceId":"1982"},{"name":"1983","title":"1983","type":"number","rdfType":"http://www.w3.org/2001/XMLSchema#decimal","dwSourceId":"1983"},{"name":"1984","title":"1984","type":"number","rdfType":"http://www.w3.org/2001/XMLSchema#decimal","dwSourceId":"1984"},{"name":"1985","title":"1985","type":"number","rdfType":"http://www.w3.org/2001/XMLSchema#decimal","dwSourceId":"1985"},{"name":"1986","title":"1986","type":"number","rdfType":"http://www.w3.org/2001/XMLSchema#decimal","dwSourceId":"1986"},{"name":"1987","title":"1987","type":"number","rdfType":"http://www.w3.org/2001/XMLSchema#decimal","dwSourceId":"1987"},{"name":"1988","title":"1988","type":"number","rdfType":"http://www.w3.org/2001/XMLSchema#decimal","dwSourceId":"1988"},{"name":"1989","title":"1989","type":"number","rdfType":"http://www.w3.org/2001/XMLSchema#decimal","dwSourceId":"1989"},{"name":"1990","title":"1990","type":"number","rdfType":"http://www.w3.org/2001/XMLSchema#decimal","dwSourceId":"1990"},{"name":"1991","title":"1991","type":"number","rdfType":"http://www.w3.org/2001/XMLSchema#decimal","dwSourceId":"1991"},{"name":"1992","title":"1992","type":"number","rdfType":"http://www.w3.org/2001/XMLSchema#decimal","dwSourceId":"1992"},{"name":"1993","title":"1993","type":"number","rdfType":"http://www.w3.org/2001/XMLSchema#decimal","dwSourceId":"1993"},{"name":"1994","title":"1994","type":"number","rdfType":"http://www.w3.org/2001/XMLSchema#decimal","dwSourceId":"1994"},{"name":"1995","title":"1995","type":"number","rdfType":"http://www.w3.org/2001/XMLSchema#decimal","dwSourceId":"1995"},{"name":"1996","title":"1996","type":"number","rdfType":"http://www.w3.org/2001/XMLSchema#decimal","dwSourceId":"1996"},{"name":"1997","title":"1997","type":"number","rdfType":"http://www.w3.org/2001/XMLSchema#decimal","dwSourceId":"1997"},{"name":"1998","title":"1998","type":"number","rdfType":"http://www.w3.org/2001/XMLSchema#decimal","dwSourceId":"1998"},{"name":"1999","title":"1999","type":"number","rdfType":"http://www.w3.org/2001/XMLSchema#decimal","dwSourceId":"1999"},{"name":"2000","title":"2000","type":"number","rdfType":"http://www.w3.org/2001/XMLSchema#decimal","dwSourceId":"2000"},{"name":"2001","title":"2001","type":"number","rdfType":"http://www.w3.org/2001/XMLSchema#decimal","dwSourceId":"2001"},{"name":"2002","title":"2002","type":"number","rdfType":"http://www.w3.org/2001/XMLSchema#decimal","dwSourceId":"2002"},{"name":"2003","title":"2003","type":"number","rdfType":"http://www.w3.org/2001/XMLSchema#decimal","dwSourceId":"2003"},{"name":"2004","title":"2004","type":"number","rdfType":"http://www.w3.org/2001/XMLSchema#decimal","dwSourceId":"2004"},{"name":"2005","title":"2005","type":"number","rdfType":"http://www.w3.org/2001/XMLSchema#decimal","dwSourceId":"2005"},{"name":"2006","title":"2006","type":"number","rdfType":"http://www.w3.org/2001/XMLSchema#decimal","dwSourceId":"2006"},{"name":"2007","title":"2007","type":"number","rdfType":"http://www.w3.org/2001/XMLSchema#decimal","dwSourceId":"2007"},{"name":"2008","title":"2008","type":"number","rdfType":"http://www.w3.org/2001/XMLSchema#decimal","dwSourceId":"2008"},{"name":"2009","title":"2009","type":"number","rdfType":"http://www.w3.org/2001/XMLSchema#decimal","dwSourceId":"2009"},{"name":"2010","title":"2010","type":"number","rdfType":"http://www.w3.org/2001/XMLSchema#decimal","dwSourceId":"2010"},{"name":"2011","title":"2011","type":"number","rdfType":"http://www.w3.org/2001/XMLSchema#decimal","dwSourceId":"2011"},{"name":"2012","title":"2012","type":"number","rdfType":"http://www.w3.org/2001/XMLSchema#decimal","dwSourceId":"2012"},{"name":"2013","title":"2013","type":"number","rdfType":"http://www.w3.org/2001/XMLSchema#decimal","dwSourceId":"2013"},{"name":"2014","title":"2014","type":"number","rdfType":"http://www.w3.org/2001/XMLSchema#decimal","dwSourceId":"2014"},{"name":"2015","title":"2015","type":"number","rdfType":"http://www.w3.org/2001/XMLSchema#decimal","dwSourceId":"2015"},{"name":"2016","title":"2016","type":"number","rdfType":"http://www.w3.org/2001/XMLSchema#decimal","dwSourceId":"2016"}]},"path":"data/gender_stat_data.csv","format":"csv"},{"name":"gender_stat_footnote","schema":{"fields":[{"name":"countrycode","title":"CountryCode","type":"string","rdfType":"http://www.w3.org/2001/XMLSchema#string","dwSourceId":"countrycode"},{"name":"seriescode","title":"SeriesCode","type":"string","rdfType":"http://www.w3.org/2001/XMLSchema#string","dwSourceId":"seriescode"},{"name":"year","title":"Year","type":"string","rdfType":"http://www.w3.org/2001/XMLSchema#string","dwSourceId":"year"},{"name":"description","title":"DESCRIPTION","type":"string","rdfType":"http://www.w3.org/2001/XMLSchema#string","dwSourceId":"description"}]},"path":"data/gender_stat_footnote.csv","format":"csv"},{"name":"gender_stat_series","schema":{"fields":[{"name":"series_code","title":"Series Code","type":"string","rdfType":"http://www.w3.org/2001/XMLSchema#string","dwSourceId":"series_code"},{"name":"topic","title":"Topic","type":"string","rdfType":"http://www.w3.org/2001/XMLSchema#string","dwSourceId":"topic"},{"name":"indicator_name","title":"Indicator Name","type":"string","rdfType":"http://www.w3.org/2001/XMLSchema#string","dwSourceId":"indicator_name"},{"name":"short_definition","title":"Short definition","type":"string","rdfType":"http://www.w3.org/2001/XMLSchema#string","dwSourceId":"short_definition"},{"name":"long_definition","title":"Long definition","type":"string","rdfType":"http://www.w3.org/2001/XMLSchema#string","dwSourceId":"long_definition"},{"name":"unit_of_measure","title":"Unit of measure","type":"string","rdfType":"http://www.w3.org/2001/XMLSchema#string","dwSourceId":"unit_of_measure"},{"name":"periodicity","title":"Periodicity","type":"string","rdfType":"http://www.w3.org/2001/XMLSchema#string","dwSourceId":"periodicity"},{"name":"base_period","title":"Base Period","type":"integer","rdfType":"http://www.w3.org/2001/XMLSchema#integer","dwSourceId":"base_period"},{"name":"other_notes","title":"Other notes","type":"string","rdfType":"http://www.w3.org/2001/XMLSchema#string","dwSourceId":"other_notes"},{"name":"aggregation_method","title":"Aggregation method","type":"string","rdfType":"http://www.w3.org/2001/XMLSchema#string","dwSourceId":"aggregation_method"},{"name":"limitations_and_exceptions","title":"Limitations and exceptions","type":"string","rdfType":"http://www.w3.org/2001/XMLSchema#string","dwSourceId":"limitations_and_exceptions"},{"name":"notes_from_original_source","title":"Notes from original source","type":"string","rdfType":"http://www.w3.org/2001/XMLSchema#string","dwSourceId":"notes_from_original_source"},{"name":"general_comments","title":"General comments","type":"string","rdfType":"http://www.w3.org/2001/XMLSchema#string","dwSourceId":"general_comments"},{"name":"source","title":"Source","type":"string","rdfType":"http://www.w3.org/2001/XMLSchema#string","dwSourceId":"source"},{"name":"statistical_concept_and_methodology","title":"Statistical concept and methodology","type":"string","rdfType":"http://www.w3.org/2001/XMLSchema#string","dwSourceId":"statistical_concept_and_methodology"},{"name":"development_relevance","title":"Development relevance","type":"string","rdfType":"http://www.w3.org/2001/XMLSchema#string","dwSourceId":"development_relevance"},{"name":"related_source_links","title":"Related source links","type":"string","rdfType":"http://www.w3.org/2001/XMLSchema#string","dwSourceId":"related_source_links"},{"name":"other_web_links","title":"Other web links","type":"string","rdfType":"http://www.w3.org/2001/XMLSchema#string","dwSourceId":"other_web_links"},{"name":"related_indicators","title":"Related indicators","type":"string","rdfType":"http://www.w3.org/2001/XMLSchema#string","dwSourceId":"related_indicators"},{"name":"license_type","title":"License Type","type":"string","rdfType":"http://www.w3.org/2001/XMLSchema#string","dwSourceId":"license_type"}]},"path":"data/gender_stat_series.csv","format":"csv"},{"name":"gender_stat_series_time","schema":{"fields":[{"name":"seriescode","title":"SeriesCode","type":"string","rdfType":"http://www.w3.org/2001/XMLSchema#string","dwSourceId":"seriescode"},{"name":"year","title":"Year","type":"string","rdfType":"http://www.w3.org/2001/XMLSchema#string","dwSourceId":"year"},{"name":"description","title":"DESCRIPTION","type":"string","rdfType":"http://www.w3.org/2001/XMLSchema#string","dwSourceId":"description"}]},"path":"data/gender_stat_series_time.csv","format":"csv"},{"name":"original/Gender_Stats_csv.zip","path":"original/Gender_Stats_csv.zip","format":"zip","mediatype":"application/zip","bytes":12609428},{"name":"original/Gender_Stats_csv/Gender_Stat_Country-Series.csv","path":"original/Gender_Stats_csv/Gender_Stat_Country-Series.csv","format":"csv","mediatype":"text/csv","bytes":171214},{"name":"original/Gender_Stats_csv/Gender_Stat_Country.csv","path":"original/Gender_Stats_csv/Gender_Stat_Country.csv","format":"csv","mediatype":"text/csv","bytes":154618},{"name":"original/Gender_Stats_csv/Gender_Stat_Data.csv","path":"original/Gender_Stats_csv/Gender_Stat_Data.csv","format":"csv","mediatype":"text/csv","bytes":64814507},{"name":"original/Gender_Stats_csv/Gender_Stat_FootNote.csv","path":"original/Gender_Stats_csv/Gender_Stat_FootNote.csv","format":"csv","mediatype":"text/csv","bytes":40407531},{"name":"original/Gender_Stats_csv/Gender_Stat_Series-Time.csv","path":"original/Gender_Stats_csv/Gender_Stat_Series-Time.csv","format":"csv","mediatype":"text/csv","bytes":7830},{"name":"original/Gender_Stats_csv/Gender_Stat_Series.csv","path":"original/Gender_Stats_csv/Gender_Stat_Series.csv","format":"csv","mediatype":"text/csv","bytes":1228463}],"keywords":["gender","statistics"]}